corrector
detector
stereoids
