Metadata-Version: 1.0
Name: stereoids
Version: 0.2.8
Summary: a simple library for 3d positioning markers via stereo vision
Home-page: https://github.com/sebastian-tschen/stereoids
Author: Sebastian Behrens
Author-email: sebastian.tschen.behrens@gmail.com
License: MIT
Platform: UNKNOWN
